rdfc_runner/__init__.py
rdfc_runner/__init__.pyi
rdfc_runner/__main__.py
rdfc_runner/convertor.py
rdfc_runner/index.ttl
rdfc_runner/iterable.py
rdfc_runner/logger.py
rdfc_runner/processor.py
rdfc_runner/reader.py
rdfc_runner/runner.py
rdfc_runner/types.py
rdfc_runner/utils.py
rdfc_runner/writer.py
rdfc_runner-0.0.3.dist-info/METADATA
rdfc_runner-0.0.3.dist-info/WHEEL
rdfc_runner-0.0.3.dist-info/entry_points.txt
rdfc_runner-0.0.3.dist-info/licenses/LICENSE
rdfc_runner-0.0.3.dist-info/RECORD
