Metadata-Version: 2.4
Name: rdfc_runner
Version: 0.0.3
Summary: Python runner for RDF-Connect
Project-URL: Homepage, https://rdf-connect.github.io
Project-URL: Repository, https://github.com/rdf-connect/py-runner
Project-URL: Issues, https://github.com/rdf-connect/py-runner/issues
Author-email: Ieben Smessaert <ieben.smessaert@ugent.be>
License-Expression: MIT
License-File: LICENSE
Requires-Python: >=3.12
Requires-Dist: grpcio-tools>=1.74.0
Requires-Dist: grpcio>=1.74.0
Requires-Dist: protobuf>=6.31.1
Requires-Dist: rdfc-proto>=0.0.1
Requires-Dist: types-protobuf>=6.30.2.20250703
